Workbook
Name Bonificacion: '1-PARAMETRIZACION'!$D$10
Name cable: '1-PARAMETRIZACION'!$D$5
Name CAJA: '1-PARAMETRIZACION'!$D$4
Name caño: '1-PARAMETRIZACION'!$D$6
Name CCABLE: '1-PARAMETRIZACION'!$A$3
Name cequipos: '1-PARAMETRIZACION'!$D$7
Name cotiza: '1-PARAMETRIZACION'!$D$8
Name cuadrilla: '1-PARAMETRIZACION'!$D$13
Name DH: '1-PARAMETRIZACION'!$D$2
Name HH: '1-PARAMETRIZACION'!$D$3
Name Imprevisto: '1-PARAMETRIZACION'!$D$9
Name km: '1-PARAMETRIZACION'!$D$18
Name mc_log: '1-PARAMETRIZACION'!$D$17
Name mc_mat: '1-PARAMETRIZACION'!$D$14
Name mc_ser: '1-PARAMETRIZACION'!$D$15
Name mc_sub: '1-PARAMETRIZACION'!$D$16
Name plazo: '1-PARAMETRIZACION'!$D$11
Name rhxcuadrilla: '1-PARAMETRIZACION'!$D$12

Sheet 0-GUIA
A1: Hojas | B1: Descripción | C1: Contenidos
A2: 1 | B2: PARAMETRIZACIÓN | C2: Completar tarifas, cotización USD / ARS, plazos, cuadrillas y márgenes antes de cotizar.
A3: 2 | B3: DIMENSIONAMIENTO | C3: Hoja libre para el relevamiento y el alcance del proyecto.
A4: 3 | B4: CUADRO DE RESULTADO | C4: Ventas, costos y contribución calculados desde el detalle de PD.
A5: 4 | B5: MATERIALES | C5: Lista de materiales, marcas, unidades y cantidades del proyecto.
A6: 5 | B6: PD | C6: Detalle del presupuesto: componentes, cantidades, costos unitarios, márgenes y venta. Completar las celdas de entrada; conservar las fórmulas.
A7: 6 | B7: OFERTA | C7: Renglón de oferta económica vinculado al presupuesto. Completar código y cantidad.
A8: 7 | B8: HOJA1 | C8: Catálogo de categorías y materiales de referencia.

Sheet 1-PARAMETRIZACION
A1: Parámetros | B1: Descripción | C1: Variable | D1: VALORES (USD)
A2: DH: Días Hombre | B2: Costo directo por día de trabajo | C2: DH
A3: HH: Hora Hombre | B3: Costo directo por hora de trabajo | C3: HH | D3: =IF(D2="","",+D2/8)
A4: Costo x Caja (un) | B4: Costo directo por instalación de caja | C4: caja
A5: Costo x Cableado (mts) | B5: Costo directo por tendido de cableado | C5: cable
A6: Costo x Canalización (mts) | B6: Costo directo por tendido de cañerías | C6: caño
A7: Costo por instalacion de equipos | B7: Costo directo por instalación de equipo | C7: cequipos
A8: Cotización dólar | B8: Valor de cotización dólar proyectada a 30 días | C8: Cotiza | F8: =IF(OR(cotiza="",DH=""),"",+cotiza*DH)
A9: Imprevistos Generales | B9: Porcetaje de imprevistos generales para el proyecto | C9: Imprevisto
A10: Bonificaciones | B10: Porcentaje de bonificación sobre valores netos | C10: Bonificacion
A11: Plazo de proyecto en días | B11: Plazo promedio de ejecución de instalaciones en sitio s sistema | C11: Plazo
A12: Recursos x cuadrilla | C12: rhxcuadrilla
A13: Ctd de cuadrillas | B13: Cuadrillas x sistema o frente de trabajo | C13: cuadrilla
A14: Margen de contribución de materiales | C14: mc_mat
A15: Margen de contribución de servicios directos | C15: mc_ser
A16: Margen de contribución de servicios tercerizados | C16: mc_sub
A17: Margen de contribución de servicios logísticos | C17: mc_log
A18: km | C18: km

Sheet 3-CUADRO DE RESULTADO
A1: Item | B1: Descripción | C1: Cuenta | D1: Importe | E1: SubTotales | F1: Observaciones
A2: 1 | B2: VENTAS | E2: =+E3 -> 0
B3: Cableado Estructurado | E3: =SUM(E4:E18) -> 0 | F3: =+E3*cotiza -> 0 | G3: =+F3*1.21 -> 0
B4: =+PD!C2 -> Rack | C4: =+SUM(D4:D10) -> 0 | D4: =IF($E$3=0,"",+E4/$E$3) | E4: =+PD!L2 -> 0
B5: =+PD!C3 -> Cableado | D5: =IF($E$3=0,"",+E5/$E$3) | E5: =+PD!L3 -> 0
B6: =+PD!C4 -> Canalizaciones | D6: =IF($E$3=0,"",+E6/$E$3) | E6: =+PD!L4 -> 0
B7: =+PD!C5 -> Terminales | D7: =IF($E$3=0,"",+E7/$E$3) | E7: =+PD!L5 -> 0
B8: =+PD!C6 -> Equipos Activos | D8: =IF($E$3=0,"",+E8/$E$3) | E8: =+PD!L6 -> 0
B9: =+PD!C7 -> Accesorios | D9: =IF($E$3=0,"",+E9/$E$3) | E9: =+PD!L7 -> 0
B10: =+PD!C8 -> Consumibles | D10: =IF($E$3=0,"",+E10/$E$3) | E10: =+PD!L8 -> 0
B11: =+PD!C9 -> Ingeniería | C11: =+SUM(D11:D17) -> 0 | D11: =IF($E$3=0,"",+E11/$E$3) | E11: =+PD!L9 -> 0
B12: =+PD!C10 -> Instalaciones y Montajes | D12: =IF($E$3=0,"",+E12/$E$3) | E12: =+PD!L10 -> 0
B13: =+PD!C11 -> Tendidos | D13: =IF($E$3=0,"",+E13/$E$3) | E13: =+PD!L11 -> 0
B14: =+PD!C12 -> Pruebas | D14: =IF($E$3=0,"",+E14/$E$3) | E14: =+PD!L12 -> 0
B15: =+PD!C13 -> Certificaciones | D15: =IF($E$3=0,"",+E15/$E$3) | E15: =+PD!L13 -> 0
B16: =+PD!C14 -> Puesta en Servicio | D16: =IF($E$3=0,"",+E16/$E$3) | E16: =+PD!L14 -> 0
B17: =+PD!C15 -> Capacitaciones | D17: =IF($E$3=0,"",+E17/$E$3) | E17: =+PD!L15 -> 0
B18: =+PD!C16 -> Servicios Logísticos | C18: =+D18 | D18: =IF($E$3=0,"",+E18/$E$3) | E18: =+PD!L16 -> 0
A20: 2 | B20: COSTOS DIRECTOS
B21: Cableado Estructurado | E21: =SUM(E22:E36) -> 0 | F21: =+E21*cotiza -> 0
B22: =+B4 -> Rack | C22: =+SUM(D22:D28) -> 0 | D22: =IF($E$21=0,"",+E22/$E$21) | E22: =+PD!J2 -> 0 | F22: =+SUM(E22:E28)*cotiza -> 0 | G22: =IF(F3=0,"",+F22/F3)
B23: =+B5 -> Cableado | D23: =IF($E$21=0,"",+E23/$E$21) | E23: =+PD!J3 -> 0
B24: =+B6 -> Canalizaciones | D24: =IF($E$21=0,"",+E24/$E$21) | E24: =+PD!J4 -> 0
B25: =+B7 -> Terminales | D25: =IF($E$21=0,"",+E25/$E$21) | E25: =+PD!J5 -> 0
B26: =+B8 -> Equipos Activos | D26: =IF($E$21=0,"",+E26/$E$21) | E26: =+PD!J6 -> 0
B27: =+B9 -> Accesorios | D27: =IF($E$21=0,"",+E27/$E$21) | E27: =+PD!J7 -> 0
B28: =+B10 -> Consumibles | D28: =IF($E$21=0,"",+E28/$E$21) | E28: =+PD!J8 -> 0
B29: =+B11 -> Ingeniería | C29: =+SUM(D29:D35) -> 0 | D29: =IF($E$21=0,"",+E29/$E$21) | E29: =+PD!J9 -> 0 | F29: =+SUM(E29:E35)*cotiza -> 0
B30: =+B12 -> Instalaciones y Montajes | D30: =IF($E$21=0,"",+E30/$E$21) | E30: =+PD!J10 -> 0
B31: =+B13 -> Tendidos | D31: =IF($E$21=0,"",+E31/$E$21) | E31: =+PD!J11 -> 0
B32: =+B14 -> Pruebas | D32: =IF($E$21=0,"",+E32/$E$21) | E32: =+PD!J12 -> 0
B33: =+B15 -> Certificaciones | D33: =IF($E$21=0,"",+E33/$E$21) | E33: =+PD!J13 -> 0
B34: =+B16 -> Puesta en Servicio | D34: =IF($E$21=0,"",+E34/$E$21) | E34: =+PD!J14 -> 0
B35: =+B17 -> Capacitaciones | D35: =IF($E$21=0,"",+E35/$E$21) | E35: =+PD!J15 -> 0
B36: =+B18 -> Servicios Logísticos | C36: =+D36 | D36: =IF($E$21=0,"",+E36/$E$21) | E36: =+PD!J16 -> 0 | F36: =+E36*cotiza -> 0
A39: 3 | B39: CONTRIBUCIÓN MARGINAL
D40: =IF(E2=0,"",+E40/E2) | E40: =+E3-E21 -> 0
A43: 4 | B43: C. FINANCIEROS Y COMERCIALES
B44: Comisiones Comerciales | E44: =+E2*D44 -> 0
B45: Elaboración de oferta
B46: Costos financieros
B47: Sellado de OC

Sheet 2-DIMENSIONAMIENTO

Sheet 6-OFERTA
A1: Número renglón | B1: Código del ítem | C1: Descripción | D1: Cantidad | E1: Precio Total
A2: 1 | C2: SERVICIO DE CABLEADO ESTRUCTURADO | E2: =ROUNDUP(+(PD!L1*cotiza)*1.21,0) -> 0 | F2: =+E2/49 -> 0
F3: =IF(cotiza=0,"",+F2/cotiza)

Sheet materiales
A1: Descripción | B1: Marca | C1: Unidad | D1: Cantidad
A2: CABLEADO ESTRUCTURADO
A3: Faceplate | B3: Commscope | C3: UN
A4: Jack Cat.5E | B4: Commscope | C4: UN
A5: Patch cord 1 mts Cat.5E | B5: Commscope | C5: UN
A6: Patch cord 1.8 mts Cat.5E | B6: Commscope | C6: UN
A7: ELECTRICIDAD
A8: Disyuntor diferencial 2x25amp | B8: Schneider | C8: UN
A9: Termomagmeticas 2x16amp | B9: Schneider | C9: UN

Sheet PD
A1: CE | B1: Cuenta | C1: CABLEADO ESTRUCTURADO | I1: =(+J1*cotiza)*1.21 -> 0 | J1: =SUM(J2:J16) -> 0 | K1: =IF(L1=0,"",+(L1-J1)/L1) | L1: =SUM(L2:L16) -> 0 | M1: =+L1*cotiza -> 0 | N1: =+L1/13 -> 0 | O1: =+N1+M1 -> 0 | P1: =+O1*1.21 -> 0
A2: 1 | C2: Rack | G2: =SUM(I2:I8) -> 0 | I2: =IF($J$1=0,"",+J2/$J$1) | J2: =+J18 -> 0 | K2: =IF(L2=0,"",+(L2-J2)/L2) | L2: =+L18 -> 0
A3: 2 | C3: Cableado | I3: =IF($J$1=0,"",+J3/$J$1) | J3: =+J26 -> 0 | K3: =IF(L3=0,"",+(L3-J3)/L3) | L3: =+L26 -> 0
A4: 3 | C4: Canalizaciones | I4: =IF($J$1=0,"",+J4/$J$1) | J4: =+J30 -> 0 | K4: =IF(L4=0,"",+(L4-J4)/L4) | L4: =+L30 -> 0
A5: 4 | C5: Terminales | I5: =IF($J$1=0,"",+J5/$J$1) | J5: =+J35 -> 0 | K5: =IF(L5=0,"",+(L5-J5)/L5) | L5: =+L35 -> 0
A6: 5 | C6: Equipos Activos | I6: =IF($J$1=0,"",+J6/$J$1) | J6: =+J43 -> 0 | K6: =IF(L6=0,"",+(L6-J6)/L6) | L6: =+L43 -> 0
A7: 6 | C7: Accesorios | I7: =IF($J$1=0,"",+J7/$J$1) | J7: =+J49 -> 0 | K7: =IF(L7=0,"",+(L7-J7)/L7) | L7: =+L49 -> 0
A8: 7 | C8: Consumibles | I8: =IF($J$1=0,"",+J8/$J$1) | J8: =+J58 -> 0 | K8: =IF(L8=0,"",+(L8-J8)/L8) | L8: =+L58 -> 0
A9: 8 | C9: Ingeniería | G9: =SUM(I9:I15) -> 0 | I9: =IF($J$1=0,"",+J9/$J$1) | J9: =+J62 -> 0 | K9: =IF(L9=0,"",+(L9-J9)/L9) | L9: =+L62 -> 0
A10: 9 | C10: Instalaciones y Montajes | I10: =IF($J$1=0,"",+J10/$J$1) | J10: =+J67 -> 0 | K10: =IF(L10=0,"",+(L10-J10)/L10) | L10: =+L67 -> 0
A11: 10 | C11: Tendidos | I11: =IF($J$1=0,"",+J11/$J$1) | J11: =+J74 -> 0 | K11: =IF(L11=0,"",+(L11-J11)/L11) | L11: =+L74 -> 0
A12: 11 | C12: Pruebas | I12: =IF($J$1=0,"",+J12/$J$1) | J12: =+J78 -> 0 | K12: =IF(L12=0,"",+(L12-J12)/L12) | L12: =+L78 -> 0
A13: 12 | C13: Certificaciones | I13: =IF($J$1=0,"",+J13/$J$1) | J13: =+J81 -> 0 | K13: =IF(L13=0,"",+(L13-J13)/L13) | L13: =+L81 -> 0
A14: 13 | C14: Puesta en Servicio | I14: =IF($J$1=0,"",+J14/$J$1) | J14: =+J85 -> 0 | K14: =IF(L14=0,"",+(L14-J14)/L14) | L14: =+L85 -> 0
A15: 14 | C15: Capacitaciones | I15: =IF($J$1=0,"",+J15/$J$1) | J15: =+J89 -> 0 | K15: =IF(L15=0,"",+(L15-J15)/L15) | L15: =+L89 -> 0
A16: 15 | C16: Servicios Logísticos | G16: =+I16 | I16: =IF($J$1=0,"",+J16/$J$1) | J16: =+J93 -> 0 | K16: =IF(L16=0,"",+(L16-J16)/L16) | L16: =+L93 -> 0
A17: Ítem | B17: Artículo | C17: Componentes del Sistema | D17: Observaciones | E17: Marca | F17: Modelo | G17: UN | H17: Ctd | I17: Costo unitario USD | J17: Costo total USD | K17: CM (%) | L17: Venta USD | M17: Venta ARS
A18: 1 | C18: =+C2 -> Rack | J18: =SUM(J19:J25) -> 0 | L18: =SUM(L19:L25) -> 0 | M18: =+L18*cotiza -> 0 | P18: =IF(H36=0,"",+P1/H36)
J19: =+I19*H19 -> 0 | K19: =+mc_mat -> 0 | L19: =+(J19 / (1-K19)) -> 0
J20: =+I20*H20 -> 0 | K20: =+mc_mat -> 0 | L20: =+(J20 / (1-K20)) -> 0
J21: =+I21*H21 -> 0 | K21: =+mc_mat -> 0 | L21: =+(J21 / (1-K21)) -> 0
J22: =+I22*H22 -> 0 | K22: =+mc_mat -> 0 | L22: =+(J22 / (1-K22)) -> 0
J23: =+I23*H23 -> 0 | K23: =+mc_mat -> 0 | L23: =+(J23 / (1-K23)) -> 0
J24: =+I24*H24 -> 0 | K24: =+mc_mat -> 0 | L24: =+(J24 / (1-K24)) -> 0
J25: =+I25*H25 -> 0 | K25: =+mc_mat -> 0 | L25: =+(J25 / (1-K25)) -> 0
A26: 2 | C26: =+C3 -> Cableado | J26: =SUM(J27:J29) -> 0 | L26: =SUM(L27:L29) -> 0 | M26: =+L26*cotiza -> 0
C27: Cable utp Cat.5e | G27: Bobina | J27: =+I27*H27 -> 0 | K27: =+mc_mat -> 0 | L27: =+(J27 / (1-K27)) -> 0
C28: Cable utp Cat.6 | G28: Bobina | J28: =+I28*H28 -> 0 | K28: =+mc_mat -> 0 | L28: =+(J28 / (1-K28)) -> 0
J29: =+I29*H29 -> 0 | K29: =+mc_mat -> 0 | L29: =+(J29 / (1-K29)) -> 0
A30: 3 | C30: =+C4 -> Canalizaciones | J30: =SUM(J31:J34) -> 0 | L30: =SUM(L31:L34) -> 0 | M30: =+L30*cotiza -> 0
C31: Bandeja Porta cable 100 mm | G31: mts | J31: =+I31*H31 -> 0 | K31: =+mc_mat -> 0 | L31: =+(J31 / (1-K31)) -> 0
C32: Cable canal 100x50 mm (Zoloda) | G32: mts | J32: =+I32*H32 -> 0 | K32: =+mc_mat -> 0 | L32: =+(J32 / (1-K32)) -> 0
C33: Porta bastidor para cable canal 100x50mm (Zoloda) | G33: UN | J33: =+I33*H33 -> 0 | K33: =+mc_mat -> 0 | L33: =+(J33 / (1-K33)) -> 0
J34: =+I34*H34 -> 0 | K34: =+mc_mat -> 0 | L34: =+(J34 / (1-K34)) -> 0
A35: 4 | C35: =+C5 -> Terminales | J35: =SUM(J36:J42) -> 0 | L35: =SUM(L36:L42) -> 0 | M35: =+L35*cotiza -> 0
C36: JACK RJ45 CAT5e | G36: UN | J36: =+I36*H36 -> 0 | K36: =+mc_mat -> 0 | L36: =+(J36 / (1-K36)) -> 0
C37: PATCHCORD CAT5 A 1,0MT NEGRO | G37: UN | J37: =+I37*H37 -> 0 | K37: =+mc_mat -> 0 | L37: =+(J37 / (1-K37)) -> 0
C38: PATCHCORD CAT5 A 2,0 MT NEGRO | G38: UN | J38: =+I38*H38 -> 0 | K38: =+mc_mat -> 0 | L38: =+(J38 / (1-K38)) -> 0
C39: faceplate | G39: UN | J39: =+I39*H39 -> 0 | K39: =+mc_mat -> 0 | L39: =+(J39 / (1-K39)) -> 0
J40: =+I40*H40 -> 0 | K40: =+mc_mat -> 0 | L40: =+(J40 / (1-K40)) -> 0
J41: =+I41*H41 -> 0 | K41: =+mc_mat -> 0 | L41: =+(J41 / (1-K41)) -> 0
J42: =+I42*H42 -> 0 | K42: =+mc_mat -> 0 | L42: =+(J42 / (1-K42)) -> 0
A43: 5 | C43: =+C6 -> Equipos Activos | J43: =SUM(J44:J48) -> 0 | L43: =SUM(L44:L48) -> 0
J44: =+I44*H44 -> 0 | K44: =+mc_mat -> 0 | L44: =+(J44 / (1-K44)) -> 0
J45: =+I45*H45 -> 0 | K45: =+mc_mat -> 0 | L45: =+(J45 / (1-K45)) -> 0
J46: =+I46*H46 -> 0 | K46: =+mc_mat -> 0 | L46: =+(J46 / (1-K46)) -> 0
J47: =+I47*H47 -> 0 | K47: =+mc_mat -> 0 | L47: =+(J47 / (1-K47)) -> 0
J48: =+I48*H48 -> 0 | K48: =+mc_mat -> 0 | L48: =+(J48 / (1-K48)) -> 0
A49: 6 | C49: =+C7 -> Accesorios | J49: =SUM(J50:J57) -> 0 | L49: =SUM(L50:L57) -> 0
C50: Cable Subterráneo tipo Proto libre de halógenos 3x4 mm | G50: mts | J50: =+I50*H50 -> 0 | K50: =+mc_mat -> 0 | L50: =+(J50 / (1-K50)) -> 0
C51: Cable Subterráneo tipo Proto libre de halógenos 3x2,5 mm | G51: mts | J51: =+I51*H51 -> 0 | K51: =+mc_mat -> 0 | L51: =+(J51 / (1-K51)) -> 0
C52: Interruptor Diferencial Tipo A Super Inmunizado 2x25A | G52: UN | J52: =+I52*H52 -> 0 | K52: =+mc_mat -> 0 | L52: =+(J52 / (1-K52)) -> 0
C53: Interruptor Termomagnético Curva C 2x16A | G53: UN | J53: =+I53*H53 -> 0 | K53: =+mc_mat -> 0 | L53: =+(J53 / (1-K53)) -> 0
C54: Tomacorriente Doble linea Roda, Covre o Kalop | G54: UN | J54: =+I54*H54 -> 0 | K54: =+mc_mat -> 0 | L54: =+(J54 / (1-K54)) -> 0
C55: Bornera p/riel Din 4mm | G55: UN | J55: =+I55*H55 -> 0 | K55: =+mc_mat -> 0 | L55: =+(J55 / (1-K55)) -> 0
C56: Bornera p/riel Din 4mm | G56: UN | J56: =+I56*H56 -> 0 | K56: =+mc_mat -> 0 | L56: =+(J56 / (1-K56)) -> 0
C57: Caja de Aluminio para borneras eléctricas 150x150x50 mm | G57: UN | J57: =+I57*H57 -> 0 | K57: =+mc_mat -> 0 | L57: =+(J57 / (1-K57)) -> 0
A58: 7 | C58: =+C8 -> Consumibles | J58: =SUM(J59:J61) -> 0 | L58: =SUM(L59:L61) -> 0 | M58: =+L58*cotiza -> 0
C59: Materiales Varios | G59: GB | I59: =+(J30+J35+J18+J26+J49)*0.1 -> 0 | J59: =+I59*H59 -> 0 | K59: =+mc_mat -> 0 | L59: =+(J59 / (1-K59)) -> 0
J60: =+I60*H60 -> 0 | K60: =+mc_mat -> 0 | L60: =+(J60 / (1-K60)) -> 0
J61: =+I61*H61 -> 0 | K61: =+mc_mat -> 0 | L61: =+(J61 / (1-K61)) -> 0
A62: 8 | C62: =+C9 -> Ingeniería | J62: =SUM(J63:J66) -> 0 | L62: =SUM(L63:L66) -> 0 | M62: =+L62*cotiza -> 0
C63: Diseño de red | G63: DH | I63: =+DH -> 0 | J63: =+I63*H63 -> 0 | K63: =+mc_ser -> 0 | L63: =+(J63 / (1-K63)) -> 0
C64: Documentación y planos | G64: DH | I64: =+DH -> 0 | J64: =+I64*H64 -> 0 | K64: =+mc_ser -> 0 | L64: =+(J64 / (1-K64)) -> 0
C65: Memoria destrictiva | G65: DH | I65: =+DH -> 0 | J65: =+I65*H65 -> 0 | K65: =+mc_ser -> 0 | L65: =+(J65 / (1-K65)) -> 0
C66: Gestion de compra | G66: DH | I66: =+DH -> 0 | J66: =+I66*H66 -> 0 | K66: =+mc_ser -> 0 | L66: =+(J66 / (1-K66)) -> 0
A67: 9 | C67: =+C10 -> Instalaciones y Montajes | D67: =+(+H68+H70+H79+H86+H71+H72+H73+H69) -> 0 | E67: =ROUNDUP(+(D67)/4,0) -> 0 | J67: =SUM(J68:J73) -> 0 | L67: =SUM(L68:L73) -> 0 | M67: =+L67*cotiza -> 0
C68: armado de rack | G68: DH | I68: =+DH -> 0 | J68: =+I68*H68 -> 0 | K68: =+mc_ser -> 0 | L68: =+(J68 / (1-K68)) -> 0
C69: puesto doble | G69: DH | H69: =+D69*2.5 -> 0 | I69: =+DH -> 0 | J69: =+I69*H69 -> 0 | K69: =+mc_ser -> 0 | L69: =+(J69 / (1-K69)) -> 0
C70: puesto simple | G70: DH | H70: =+D70*1.5 -> 0 | I70: =+DH -> 0 | J70: =+I70*H70 -> 0 | K70: =+mc_ser -> 0 | L70: =+(J70 / (1-K70)) -> 0
C71: interack | G71: DH | H71: =+D71*1 -> 0 | I71: =+DH -> 0 | J71: =+I71*H71 -> 0 | K71: =+mc_ser -> 0 | L71: =+(J71 / (1-K71)) -> 0
J72: =+I72*H72 -> 0 | K72: =+mc_ser -> 0 | L72: =+(J72 / (1-K72)) -> 0
J73: =+I73*H73 -> 0 | K73: =+mc_ser -> 0 | L73: =+(J73 / (1-K73)) -> 0
A74: 10 | C74: =+C11 -> Tendidos | J74: =SUM(J75:J77) -> 0 | L74: =SUM(L75:L77) -> 0
J75: =+I75*H75 -> 0 | K75: =+mc_ser -> 0 | L75: =+(J75 / (1-K75)) -> 0
J76: =+I76*H76 -> 0 | K76: =+mc_ser -> 0 | L76: =+(J76 / (1-K76)) -> 0
J77: =+I77*H77 -> 0 | K77: =+mc_ser -> 0 | L77: =+(J77 / (1-K77)) -> 0
A78: 11 | C78: =+C12 -> Pruebas | J78: =SUM(J79:J80) -> 0 | L78: =SUM(L79:L80) -> 0
C79: Pruebas | G79: DH | I79: =+DH -> 0 | J79: =+I79*H79 -> 0 | K79: =+mc_ser -> 0 | L79: =+(J79 / (1-K79)) -> 0
J80: =+I80*H80 -> 0 | K80: =+mc_ser -> 0 | L80: =+(J80 / (1-K80)) -> 0
A81: 12 | C81: =+C13 -> Certificaciones | J81: =SUM(J82:J84) -> 0 | L81: =SUM(L82:L84) -> 0
C82: Certificación de puestos | G82: UN | H82: =+H36 -> 0 | J82: =+I82*H82 -> 0 | K82: =+mc_ser -> 0 | L82: =+(J82 / (1-K82)) -> 0
J83: =+I83*H83 -> 0 | K83: =+mc_ser -> 0 | L83: =+(J83 / (1-K83)) -> 0
J84: =+I84*H84 -> 0 | K84: =+mc_ser -> 0 | L84: =+(J84 / (1-K84)) -> 0
A85: 13 | C85: =+C14 -> Puesta en Servicio | J85: =SUM(J86:J88) -> 0 | L85: =SUM(L86:L88) -> 0
C86: Verificación de conectividad | G86: DH | I86: =+DH -> 0 | J86: =+I86*H86 -> 0 | K86: =+mc_ser -> 0 | L86: =+(J86 / (1-K86)) -> 0
J87: =+I87*H87 -> 0 | K87: =+mc_ser -> 0 | L87: =+(J87 / (1-K87)) -> 0
A89: 14 | C89: =+C15 -> Capacitaciones | J89: =SUM(J90:J92) -> 0 | L89: =SUM(L90:L92) -> 0
C90: Transferencia del sistema | G90: DH | I90: =+DH -> 0 | J90: =+I90*H90 -> 0 | K90: =+mc_ser -> 0 | L90: =+(J90 / (1-K90)) -> 0
C91: Garantía | G91: DH | I91: =+DH -> 0 | J91: =+I91*H91 -> 0 | K91: =+mc_ser -> 0 | L91: =+(J91 / (1-K91)) -> 0
A93: 15 | C93: =+C16 -> Servicios Logísticos | J93: =+J94+J106+J111+J114+J117 -> 0 | L93: =+L94+L106+L111+L114+L117 -> 0 | M93: =+L93*cotiza -> 0
A94: 15.1 | C94: Fletes y Seguros | J94: =SUM(J95:J105) -> 0 | L94: =SUM(L95:L105) -> 0
C95: flete | G95: GB | I95: =+(J18+J26+J30+J35+J43+J49)*0.07 -> 0 | J95: =+I95*H95 -> 0 | K95: =+mc_log -> 0 | L95: =+(J95 / (1-K95)) -> 0
C96: seguro | G96: GB | J96: =+I96*H96 -> 0 | K96: =+mc_log -> 0 | L96: =+(J96 / (1-K96)) -> 0
J97: =+I97*H97 -> 0 | K97: =+mc_log -> 0 | L97: =+(J97 / (1-K97)) -> 0
J98: =+I98*H98 -> 0 | K98: =+mc_log -> 0 | L98: =+(J98 / (1-K98)) -> 0
J99: =+I99*H99 -> 0 | K99: =+mc_log -> 0 | L99: =+(J99 / (1-K99)) -> 0
J100: =+I100*H100 -> 0 | K100: =+mc_log -> 0 | L100: =+(J100 / (1-K100)) -> 0
J101: =+I101*H101 -> 0 | K101: =+mc_log -> 0 | L101: =+(J101 / (1-K101)) -> 0
J102: =+I102*H102 -> 0 | K102: =+mc_log -> 0 | L102: =+(J102 / (1-K102)) -> 0
...

Sheet Hoja1
C29: Categoría | D29: Material
C30: Cableado | D30: Cable UTP Cat.5e
D31: Cable UTP Cat.6
C33: Canalizaciones | D33: Bandeja Portacables 100 mm
D34: Cable Canal 100x50 mm (Zoloda)
D35: Porta Bastidor para Cable Canal 100x50mm (Zoloda)
C37: Terminales | D37: JACK RJ45 CAT5e
D38: Patchcord CAT5 a 1,0m Negro
D39: Patchcord CAT5 a 2,0m Negro
D40: Faceplate
C42: Equipos Activos
C43: Accesorios | D43: Cable Subterráneo Tipo Proto Libre de Halógenos 3x4 mm
D44: Cable Subterráneo Tipo Proto Libre de Halógenos 3x2,5 mm
D45: Interruptor Diferencial Tipo A Super Inmunizado 2x25A
D46: Interruptor Termomagnético Curva C 2x16A
D47: Tomacorriente Doble Línea Roda, Covre o Kalop
D48: Bornera para Riel DIN 4mm
D49: Bornera para Riel DIN 4mm
D50: Caja de Aluminio para Borneras Eléctricas 150x150x50 mm
